{
  "generated_at": "2026-02-27T11:34:30.820649Z",
  "events": [
    {
      "id": "a8edcabe0d5c488f",
      "kind": "report_new",
      "title": "New high-signal report",
      "message": "Aussie Players Getting Frequently Put In Singapore Servers",
      "severity_key": "stable",
      "occurred_at": "2026-02-27T11:34:30.820649Z",
      "links": [
        "https://us.forums.blizzard.com/en/overwatch/t/aussie-players-getting-frequently-put-in-singapore-servers/1005969"
      ],
      "relay": {
        "discord": {
          "content": "**New high-signal report**\nAussie Players Getting Frequently Put In Singapore Servers\nhttps://us.forums.blizzard.com/en/overwatch/t/aussie-players-getting-frequently-put-in-singapore-servers/1005969"
        },
        "telegram": {
          "text": "<b>New high-signal report</b>\nAussie Players Getting Frequently Put In Singapore Servers\nhttps://us.forums.blizzard.com/en/overwatch/t/aussie-players-getting-frequently-put-in-singapore-servers/1005969",
          "parse_mode": "HTML",
          "disable_web_page_preview": false
        }
      }
    },
    {
      "id": "735a3adbc0812414",
      "kind": "report_new",
      "title": "New high-signal report",
      "message": "Playing in AUS and getting put on US servers",
      "severity_key": "stable",
      "occurred_at": "2026-02-27T11:34:30.820649Z",
      "links": [
        "https://us.forums.blizzard.com/en/overwatch/t/playing-in-aus-and-getting-put-on-us-servers/1005966"
      ],
      "relay": {
        "discord": {
          "content": "**New high-signal report**\nPlaying in AUS and getting put on US servers\nhttps://us.forums.blizzard.com/en/overwatch/t/playing-in-aus-and-getting-put-on-us-servers/1005966"
        },
        "telegram": {
          "text": "<b>New high-signal report</b>\nPlaying in AUS and getting put on US servers\nhttps://us.forums.blizzard.com/en/overwatch/t/playing-in-aus-and-getting-put-on-us-servers/1005966",
          "parse_mode": "HTML",
          "disable_web_page_preview": false
        }
      }
    }
  ],
  "unread_count": 2,
  "webhook_examples": {
    "discord": "POST relay.discord JSON body to your Discord webhook URL.",
    "telegram": "POST relay.telegram JSON body to https://api.telegram.org/bot<token>/sendMessage."
  }
}