{
  "generated_at": "2026-03-06T19:55:14.847650Z",
  "events": [
    {
      "id": "db8fa0e70f06e2b6",
      "kind": "report_new",
      "title": "New high-signal report",
      "message": "Fix your game Blizzard - Stadium and Rendering Device Lost",
      "severity_key": "stable",
      "occurred_at": "2026-03-06T19:55:14.847650Z",
      "links": [
        "https://us.forums.blizzard.com/en/overwatch/t/fix-your-game-blizzard-stadium-and-rendering-device-lost/1007450"
      ],
      "relay": {
        "discord": {
          "content": "**New high-signal report**\nFix your game Blizzard - Stadium and Rendering Device Lost\nhttps://us.forums.blizzard.com/en/overwatch/t/fix-your-game-blizzard-stadium-and-rendering-device-lost/1007450"
        },
        "telegram": {
          "text": "<b>New high-signal report</b>\nFix your game Blizzard - Stadium and Rendering Device Lost\nhttps://us.forums.blizzard.com/en/overwatch/t/fix-your-game-blizzard-stadium-and-rendering-device-lost/1007450",
          "parse_mode": "HTML",
          "disable_web_page_preview": false
        }
      }
    },
    {
      "id": "59e5037f5dc8353b",
      "kind": "report_new",
      "title": "New high-signal report",
      "message": "Ping rising up to 300ms since yesterday",
      "severity_key": "stable",
      "occurred_at": "2026-03-06T19:55:14.847650Z",
      "links": [
        "https://us.forums.blizzard.com/en/overwatch/t/ping-rising-up-to-300ms-since-yesterday/1007402"
      ],
      "relay": {
        "discord": {
          "content": "**New high-signal report**\nPing rising up to 300ms since yesterday\nhttps://us.forums.blizzard.com/en/overwatch/t/ping-rising-up-to-300ms-since-yesterday/1007402"
        },
        "telegram": {
          "text": "<b>New high-signal report</b>\nPing rising up to 300ms since yesterday\nhttps://us.forums.blizzard.com/en/overwatch/t/ping-rising-up-to-300ms-since-yesterday/1007402",
          "parse_mode": "HTML",
          "disable_web_page_preview": false
        }
      }
    }
  ],
  "unread_count": 2,
  "webhook_examples": {
    "discord": "POST relay.discord JSON body to your Discord webhook URL.",
    "telegram": "POST relay.telegram JSON body to https://api.telegram.org/bot<token>/sendMessage."
  }
}