{
  "generated_at": "2026-02-16T20:35:33.810698Z",
  "events": [
    {
      "id": "7b444fd2dd6d8f0a",
      "kind": "report_new",
      "title": "New high-signal report",
      "message": "Stadium Icons Need To Be Reverted",
      "severity_key": "stable",
      "occurred_at": "2026-02-16T20:35:33.810698Z",
      "links": [
        "https://us.forums.blizzard.com/en/overwatch/t/stadium-icons-need-to-be-reverted/1000882"
      ],
      "relay": {
        "discord": {
          "content": "**New high-signal report**\nStadium Icons Need To Be Reverted\nhttps://us.forums.blizzard.com/en/overwatch/t/stadium-icons-need-to-be-reverted/1000882"
        },
        "telegram": {
          "text": "<b>New high-signal report</b>\nStadium Icons Need To Be Reverted\nhttps://us.forums.blizzard.com/en/overwatch/t/stadium-icons-need-to-be-reverted/1000882",
          "parse_mode": "HTML",
          "disable_web_page_preview": false
        }
      }
    },
    {
      "id": "1f21825d93b1bdbd",
      "kind": "report_new",
      "title": "New high-signal report",
      "message": "Overwatch 1 merger issues",
      "severity_key": "stable",
      "occurred_at": "2026-02-16T20:35:33.810698Z",
      "links": [
        "https://us.forums.blizzard.com/en/overwatch/t/overwatch-1-merger-issues/770594"
      ],
      "relay": {
        "discord": {
          "content": "**New high-signal report**\nOverwatch 1 merger issues\nhttps://us.forums.blizzard.com/en/overwatch/t/overwatch-1-merger-issues/770594"
        },
        "telegram": {
          "text": "<b>New high-signal report</b>\nOverwatch 1 merger issues\nhttps://us.forums.blizzard.com/en/overwatch/t/overwatch-1-merger-issues/770594",
          "parse_mode": "HTML",
          "disable_web_page_preview": false
        }
      }
    }
  ],
  "unread_count": 2,
  "webhook_examples": {
    "discord": "POST relay.discord JSON body to your Discord webhook URL.",
    "telegram": "POST relay.telegram JSON body to https://api.telegram.org/bot<token>/sendMessage."
  }
}