{
  "generated_at": "2026-02-22T21:50:11.670308Z",
  "events": [
    {
      "id": "a319d7dc54d28356",
      "kind": "report_new",
      "title": "New high-signal report",
      "message": "[Stadium bug] Soldier item - Bomb Diffusal Boots",
      "severity_key": "stable",
      "occurred_at": "2026-02-22T21:50:11.670308Z",
      "links": [
        "https://us.forums.blizzard.com/en/overwatch/t/stadium-bug-soldier-item-bomb-diffusal-boots/1004753"
      ],
      "relay": {
        "discord": {
          "content": "**New high-signal report**\n[Stadium bug] Soldier item - Bomb Diffusal Boots\nhttps://us.forums.blizzard.com/en/overwatch/t/stadium-bug-soldier-item-bomb-diffusal-boots/1004753"
        },
        "telegram": {
          "text": "<b>New high-signal report</b>\n[Stadium bug] Soldier item - Bomb Diffusal Boots\nhttps://us.forums.blizzard.com/en/overwatch/t/stadium-bug-soldier-item-bomb-diffusal-boots/1004753",
          "parse_mode": "HTML",
          "disable_web_page_preview": false
        }
      }
    },
    {
      "id": "5deb1a80ae521af8",
      "kind": "report_new",
      "title": "New high-signal report",
      "message": "Frequent random crashes mid-match",
      "severity_key": "stable",
      "occurred_at": "2026-02-22T21:50:11.670308Z",
      "links": [
        "https://us.forums.blizzard.com/en/overwatch/t/frequent-random-crashes-mid-match/1003645"
      ],
      "relay": {
        "discord": {
          "content": "**New high-signal report**\nFrequent random crashes mid-match\nhttps://us.forums.blizzard.com/en/overwatch/t/frequent-random-crashes-mid-match/1003645"
        },
        "telegram": {
          "text": "<b>New high-signal report</b>\nFrequent random crashes mid-match\nhttps://us.forums.blizzard.com/en/overwatch/t/frequent-random-crashes-mid-match/1003645",
          "parse_mode": "HTML",
          "disable_web_page_preview": false
        }
      }
    }
  ],
  "unread_count": 2,
  "webhook_examples": {
    "discord": "POST relay.discord JSON body to your Discord webhook URL.",
    "telegram": "POST relay.telegram JSON body to https://api.telegram.org/bot<token>/sendMessage."
  }
}