{
  "generated_at": "2026-02-28T16:30:19.225233Z",
  "events": [
    {
      "id": "51ba1ebec8c7d06a",
      "kind": "report_new",
      "title": "New high-signal report",
      "message": "Crashes after update",
      "severity_key": "stable",
      "occurred_at": "2026-02-28T16:30:19.225233Z",
      "links": [
        "https://us.forums.blizzard.com/en/overwatch/t/crashes-after-update/1006253"
      ],
      "relay": {
        "discord": {
          "content": "**New high-signal report**\nCrashes after update\nhttps://us.forums.blizzard.com/en/overwatch/t/crashes-after-update/1006253"
        },
        "telegram": {
          "text": "<b>New high-signal report</b>\nCrashes after update\nhttps://us.forums.blizzard.com/en/overwatch/t/crashes-after-update/1006253",
          "parse_mode": "HTML",
          "disable_web_page_preview": false
        }
      }
    },
    {
      "id": "62448ce76d4dad1b",
      "kind": "report_new",
      "title": "New high-signal report",
      "message": "Frequently Losing Connection to Servers PC OCE",
      "severity_key": "stable",
      "occurred_at": "2026-02-28T16:30:19.225233Z",
      "links": [
        "https://us.forums.blizzard.com/en/overwatch/t/frequently-losing-connection-to-servers-pc-oce/1006252"
      ],
      "relay": {
        "discord": {
          "content": "**New high-signal report**\nFrequently Losing Connection to Servers PC OCE\nhttps://us.forums.blizzard.com/en/overwatch/t/frequently-losing-connection-to-servers-pc-oce/1006252"
        },
        "telegram": {
          "text": "<b>New high-signal report</b>\nFrequently Losing Connection to Servers PC OCE\nhttps://us.forums.blizzard.com/en/overwatch/t/frequently-losing-connection-to-servers-pc-oce/1006252",
          "parse_mode": "HTML",
          "disable_web_page_preview": false
        }
      }
    }
  ],
  "unread_count": 2,
  "webhook_examples": {
    "discord": "POST relay.discord JSON body to your Discord webhook URL.",
    "telegram": "POST relay.telegram JSON body to https://api.telegram.org/bot<token>/sendMessage."
  }
}