{
  "generated_at": "2026-03-02T17:12:57.476103Z",
  "events": [
    {
      "id": "ca9019212a2459a7",
      "kind": "report_new",
      "title": "New high-signal report",
      "message": "Weird interaction with Anrans Ult and Lifeweavers Petal",
      "severity_key": "stable",
      "occurred_at": "2026-03-02T17:12:57.476103Z",
      "links": [
        "https://us.forums.blizzard.com/en/overwatch/t/weird-interaction-with-anrans-ult-and-lifeweavers-petal/1006659"
      ],
      "relay": {
        "discord": {
          "content": "**New high-signal report**\nWeird interaction with Anrans Ult and Lifeweavers Petal\nhttps://us.forums.blizzard.com/en/overwatch/t/weird-interaction-with-anrans-ult-and-lifeweavers-petal/1006659"
        },
        "telegram": {
          "text": "<b>New high-signal report</b>\nWeird interaction with Anrans Ult and Lifeweavers Petal\nhttps://us.forums.blizzard.com/en/overwatch/t/weird-interaction-with-anrans-ult-and-lifeweavers-petal/1006659",
          "parse_mode": "HTML",
          "disable_web_page_preview": false
        }
      }
    },
    {
      "id": "999adea7a798a825",
      "kind": "report_new",
      "title": "New high-signal report",
      "message": "Ban Injusto de season no competitivo",
      "severity_key": "stable",
      "occurred_at": "2026-03-02T17:12:57.476103Z",
      "links": [
        "https://us.forums.blizzard.com/en/overwatch/t/ban-injusto-de-season-no-competitivo/1006657"
      ],
      "relay": {
        "discord": {
          "content": "**New high-signal report**\nBan Injusto de season no competitivo\nhttps://us.forums.blizzard.com/en/overwatch/t/ban-injusto-de-season-no-competitivo/1006657"
        },
        "telegram": {
          "text": "<b>New high-signal report</b>\nBan Injusto de season no competitivo\nhttps://us.forums.blizzard.com/en/overwatch/t/ban-injusto-de-season-no-competitivo/1006657",
          "parse_mode": "HTML",
          "disable_web_page_preview": false
        }
      }
    }
  ],
  "unread_count": 2,
  "webhook_examples": {
    "discord": "POST relay.discord JSON body to your Discord webhook URL.",
    "telegram": "POST relay.telegram JSON body to https://api.telegram.org/bot<token>/sendMessage."
  }
}