{
  "generated_at": "2026-03-07T22:50:10.796035Z",
  "events": [
    {
      "id": "8f07f289754bba7e",
      "kind": "report_new",
      "title": "New high-signal report",
      "message": "Profil statsen på xbox",
      "severity_key": "stable",
      "occurred_at": "2026-03-07T22:50:10.796035Z",
      "links": [
        "https://us.forums.blizzard.com/en/overwatch/t/profil-statsen-p%C3%A5-xbox/1007650"
      ],
      "relay": {
        "discord": {
          "content": "**New high-signal report**\nProfil statsen på xbox\nhttps://us.forums.blizzard.com/en/overwatch/t/profil-statsen-p%C3%A5-xbox/1007650"
        },
        "telegram": {
          "text": "<b>New high-signal report</b>\nProfil statsen på xbox\nhttps://us.forums.blizzard.com/en/overwatch/t/profil-statsen-p%C3%A5-xbox/1007650",
          "parse_mode": "HTML",
          "disable_web_page_preview": false
        }
      }
    },
    {
      "id": "cf2b82bab2a019a5",
      "kind": "report_new",
      "title": "New high-signal report",
      "message": "Not obtained Devourer Genji skin after the WoW quest",
      "severity_key": "stable",
      "occurred_at": "2026-03-07T22:50:10.796035Z",
      "links": [
        "https://us.forums.blizzard.com/en/overwatch/t/not-obtained-devourer-genji-skin-after-the-wow-quest/1006079"
      ],
      "relay": {
        "discord": {
          "content": "**New high-signal report**\nNot obtained Devourer Genji skin after the WoW quest\nhttps://us.forums.blizzard.com/en/overwatch/t/not-obtained-devourer-genji-skin-after-the-wow-quest/1006079"
        },
        "telegram": {
          "text": "<b>New high-signal report</b>\nNot obtained Devourer Genji skin after the WoW quest\nhttps://us.forums.blizzard.com/en/overwatch/t/not-obtained-devourer-genji-skin-after-the-wow-quest/1006079",
          "parse_mode": "HTML",
          "disable_web_page_preview": false
        }
      }
    }
  ],
  "unread_count": 2,
  "webhook_examples": {
    "discord": "POST relay.discord JSON body to your Discord webhook URL.",
    "telegram": "POST relay.telegram JSON body to https://api.telegram.org/bot<token>/sendMessage."
  }
}