{
  "generated_at": "2026-02-26T12:01:31.507222Z",
  "events": [
    {
      "id": "588df785d82149bd",
      "kind": "report_new",
      "title": "New high-signal report",
      "message": "Stadium competitive no armory access glitch",
      "severity_key": "stable",
      "occurred_at": "2026-02-26T12:01:31.507222Z",
      "links": [
        "https://us.forums.blizzard.com/en/overwatch/t/stadium-competitive-no-armory-access-glitch/1005198"
      ],
      "relay": {
        "discord": {
          "content": "**New high-signal report**\nStadium competitive no armory access glitch\nhttps://us.forums.blizzard.com/en/overwatch/t/stadium-competitive-no-armory-access-glitch/1005198"
        },
        "telegram": {
          "text": "<b>New high-signal report</b>\nStadium competitive no armory access glitch\nhttps://us.forums.blizzard.com/en/overwatch/t/stadium-competitive-no-armory-access-glitch/1005198",
          "parse_mode": "HTML",
          "disable_web_page_preview": false
        }
      }
    },
    {
      "id": "97fefef60c0fe661",
      "kind": "report_new",
      "title": "New high-signal report",
      "message": "Mizuki - \"Retour de katashiro\"",
      "severity_key": "stable",
      "occurred_at": "2026-02-26T12:01:31.507222Z",
      "links": [
        "https://us.forums.blizzard.com/en/overwatch/t/mizuki-retour-de-katashiro/1005764"
      ],
      "relay": {
        "discord": {
          "content": "**New high-signal report**\nMizuki - \"Retour de katashiro\"\nhttps://us.forums.blizzard.com/en/overwatch/t/mizuki-retour-de-katashiro/1005764"
        },
        "telegram": {
          "text": "<b>New high-signal report</b>\nMizuki - \"Retour de katashiro\"\nhttps://us.forums.blizzard.com/en/overwatch/t/mizuki-retour-de-katashiro/1005764",
          "parse_mode": "HTML",
          "disable_web_page_preview": false
        }
      }
    }
  ],
  "unread_count": 2,
  "webhook_examples": {
    "discord": "POST relay.discord JSON body to your Discord webhook URL.",
    "telegram": "POST relay.telegram JSON body to https://api.telegram.org/bot<token>/sendMessage."
  }
}